get_aws_details/__init__.py
get_aws_details/__init__.pyi
get_aws_details/__main__.py
get_aws_details/__main__.pyi
get_aws_details/py.typed
get_aws_details-1.1.0.data/scripts/aws_details
get_aws_details-1.1.0.dist-info/METADATA
get_aws_details-1.1.0.dist-info/WHEEL
get_aws_details-1.1.0.dist-info/entry_points.txt
get_aws_details-1.1.0.dist-info/RECORD
